block_pruner/__init__.py
block_pruner/__main__.py
block_pruner/block_pruner.py
block_pruner/match_str.py
block_pruner/version.py
block_pruner-0.0.4.dist-info/METADATA
block_pruner-0.0.4.dist-info/WHEEL
block_pruner-0.0.4.dist-info/entry_points.txt
block_pruner-0.0.4.dist-info/top_level.txt
block_pruner-0.0.4.dist-info/RECORD
